__init__.py
dli_contrast.py
price_tag.py
tools.py
tuanyou_dli.py
zhidian_dli.py
zhidian_dws.py
zhidian_hive.py
zhy_tools-0.0.2.dist-info/METADATA
zhy_tools-0.0.2.dist-info/WHEEL
zhy_tools-0.0.2.dist-info/licenses/LICENSE
zhy_tools-0.0.2.dist-info/RECORD
