Metadata-Version: 2.1
Name: zhy_tools
Version: 0.0.2
Summary: zhy_tools is a common tool package which i used on word. It will collect all kinds of tools which will be useful for my job.
Project-URL: Homepage, https://github.com/openKG-field/kgbook-2020
Author-email: 赵宏宇 <zhaohongyu2401@yeah.net>
License: MIT License
License-File: LICENSE
Classifier: License :: OSI Approved :: MIT License
Classifier: Operating System :: OS Independent
Classifier: Programming Language :: Python :: 3
Requires-Python: >=3.7
